{
  "head" : {
    "vars" : [ "item", "articlename", "itemLabel", "itemDescription" ]
  },
  "results" : {
    "bindings" : [ {
      "item" : {
        "type" : "uri",
        "value" : "http://www.wikidata.org/entity/Q16848"
      },
      "itemLabel" : {
        "xml:lang" : "en",
        "type" : "literal",
        "value" : "Paavo Nuotio"
      },
      "itemDescription" : {
        "xml:lang" : "en",
        "type" : "literal",
        "value" : "Finnish ski jumper and Nordic combined skier (1901–1968)"
      },
      "articlename" : {
        "xml:lang" : "fr",
        "type" : "literal",
        "value" : "Paavo Nuotio"
      }
    }, {
      "item" : {
        "type" : "uri",
        "value" : "http://www.wikidata.org/entity/Q3357812"
      },
      "itemLabel" : {
        "xml:lang" : "en",
        "type" : "literal",
        "value" : "Otto Heidkämper"
      },
      "itemDescription" : {
        "xml:lang" : "en",
        "type" : "literal",
        "value" : "German General and Knight's Cross Recipient (1901-1969)"
      },
      "articlename" : {
        "xml:lang" : "fr",
        "type" : "literal",
        "value" : "Otto Heidkämper"
      }
    }, {
      "item" : {
        "type" : "uri",
        "value" : "http://www.wikidata.org/entity/Q482708"
      },
      "itemLabel" : {
        "xml:lang" : "en",
        "type" : "literal",
        "value" : "Ham Seok-heon"
      },
      "itemDescription" : {
        "xml:lang" : "en",
        "type" : "literal",
        "value" : "South Korean activist and philosopher (1901–1989)"
      },
      "articlename" : {
        "xml:lang" : "fr",
        "type" : "literal",
        "value" : "Ham Seok-heon"
      }
    }, {
      "item" : {
        "type" : "uri",
        "value" : "http://www.wikidata.org/entity/Q744357"
      },
      "itemLabel" : {
        "xml:lang" : "en",
        "type" : "literal",
        "value" : "Paul Fix"
      },
      "itemDescription" : {
        "xml:lang" : "en",
        "type" : "literal",
        "value" : "American film and television character actor, best known for his work in Westerns (1901-1983)"
      },
      "articlename" : {
        "xml:lang" : "fr",
        "type" : "literal",
        "value" : "Paul Fix"
      }
    }, {
      "item" : {
        "type" : "uri",
        "value" : "http://www.wikidata.org/entity/Q17461863"
      },
      "itemLabel" : {
        "xml:lang" : "en",
        "type" : "literal",
        "value" : "Raymond Tournon"
      },
      "itemDescription" : {
        "xml:lang" : "en",
        "type" : "literal",
        "value" : "French painter (1901-1975)"
      },
      "articlename" : {
        "xml:lang" : "fr",
        "type" : "literal",
        "value" : "Raymond Tournon (fils)"
      }
    } ]
  }
}