{
  "head" : {
    "vars" : [ "item", "articlename", "itemLabel", "itemDescription" ]
  },
  "results" : {
    "bindings" : [ {
      "item" : {
        "type" : "uri",
        "value" : "http://www.wikidata.org/entity/Q23869556"
      },
      "itemLabel" : {
        "xml:lang" : "en",
        "type" : "literal",
        "value" : "Benjamin Källman"
      },
      "itemDescription" : {
        "xml:lang" : "en",
        "type" : "literal",
        "value" : "Finnish association football player"
      },
      "articlename" : {
        "xml:lang" : "fr",
        "type" : "literal",
        "value" : "Benjamin Källman"
      }
    }, {
      "item" : {
        "type" : "uri",
        "value" : "http://www.wikidata.org/entity/Q27049316"
      },
      "itemLabel" : {
        "xml:lang" : "mul",
        "type" : "literal",
        "value" : "Arnaud Nordin"
      },
      "itemDescription" : {
        "xml:lang" : "en",
        "type" : "literal",
        "value" : "French association football player"
      },
      "articlename" : {
        "xml:lang" : "fr",
        "type" : "literal",
        "value" : "Arnaud Nordin"
      }
    }, {
      "item" : {
        "type" : "uri",
        "value" : "http://www.wikidata.org/entity/Q28006837"
      },
      "itemLabel" : {
        "xml:lang" : "en",
        "type" : "literal",
        "value" : "Joel Osikel"
      },
      "itemDescription" : {
        "xml:lang" : "en",
        "type" : "literal",
        "value" : "Nigerian association football player"
      },
      "articlename" : {
        "xml:lang" : "fr",
        "type" : "literal",
        "value" : "Joel Osikel"
      }
    }, {
      "item" : {
        "type" : "uri",
        "value" : "http://www.wikidata.org/entity/Q458632"
      },
      "itemLabel" : {
        "xml:lang" : "en",
        "type" : "literal",
        "value" : "Nujood Ali"
      },
      "itemDescription" : {
        "xml:lang" : "en",
        "type" : "literal",
        "value" : "Advocate of opposition to forced marriages"
      },
      "articlename" : {
        "xml:lang" : "fr",
        "type" : "literal",
        "value" : "Nojoud Ali"
      }
    }, {
      "item" : {
        "type" : "uri",
        "value" : "http://www.wikidata.org/entity/Q39034506"
      },
      "itemLabel" : {
        "xml:lang" : "en",
        "type" : "literal",
        "value" : "Michal Hlavatý"
      },
      "itemDescription" : {
        "xml:lang" : "en",
        "type" : "literal",
        "value" : "Czech association football player"
      },
      "articlename" : {
        "xml:lang" : "fr",
        "type" : "literal",
        "value" : "Michal Hlavatý"
      }
    }, {
      "item" : {
        "type" : "uri",
        "value" : "http://www.wikidata.org/entity/Q51885236"
      },
      "itemLabel" : {
        "xml:lang" : "en",
        "type" : "literal",
        "value" : "Zeineba Yimer"
      },
      "itemDescription" : {
        "xml:lang" : "en",
        "type" : "literal",
        "value" : "Ethiopian long distance runner"
      },
      "articlename" : {
        "xml:lang" : "fr",
        "type" : "literal",
        "value" : "Zeineba Yimer"
      }
    }, {
      "item" : {
        "type" : "uri",
        "value" : "http://www.wikidata.org/entity/Q55759511"
      },
      "itemLabel" : {
        "xml:lang" : "en",
        "type" : "literal",
        "value" : "Hayden Coulson"
      },
      "itemDescription" : {
        "xml:lang" : "en",
        "type" : "literal",
        "value" : "English footballer (born 1998)"
      },
      "articlename" : {
        "xml:lang" : "fr",
        "type" : "literal",
        "value" : "Hayden Coulson"
      }
    }, {
      "item" : {
        "type" : "uri",
        "value" : "http://www.wikidata.org/entity/Q56651204"
      },
      "itemLabel" : {
        "xml:lang" : "en",
        "type" : "literal",
        "value" : "Ankita Bhakat"
      },
      "itemDescription" : {
        "xml:lang" : "en",
        "type" : "literal",
        "value" : "Indian archer"
      },
      "articlename" : {
        "xml:lang" : "fr",
        "type" : "literal",
        "value" : "Ankita Bhakat"
      }
    }, {
      "item" : {
        "type" : "uri",
        "value" : "http://www.wikidata.org/entity/Q70614744"
      },
      "itemLabel" : {
        "xml:lang" : "en",
        "type" : "literal",
        "value" : "Mattia Bevilacqua"
      },
      "itemDescription" : {
        "xml:lang" : "en",
        "type" : "literal",
        "value" : "Italian cyclist"
      },
      "articlename" : {
        "xml:lang" : "fr",
        "type" : "literal",
        "value" : "Mattia Bevilacqua"
      }
    }, {
      "item" : {
        "type" : "uri",
        "value" : "http://www.wikidata.org/entity/Q28864269"
      },
      "itemLabel" : {
        "xml:lang" : "en",
        "type" : "literal",
        "value" : "Rinsola Babajide"
      },
      "itemDescription" : {
        "xml:lang" : "en",
        "type" : "literal",
        "value" : "English-Nigerian footballer (born 1998)"
      },
      "articlename" : {
        "xml:lang" : "fr",
        "type" : "literal",
        "value" : "Rinsola Babajide"
      }
    }, {
      "item" : {
        "type" : "uri",
        "value" : "http://www.wikidata.org/entity/Q121009987"
      },
      "itemLabel" : {
        "xml:lang" : "mul",
        "type" : "literal",
        "value" : "Rémi Conroy"
      },
      "articlename" : {
        "xml:lang" : "fr",
        "type" : "literal",
        "value" : "Rémi Conroy"
      }
    }, {
      "item" : {
        "type" : "uri",
        "value" : "http://www.wikidata.org/entity/Q124623774"
      },
      "itemLabel" : {
        "xml:lang" : "mul",
        "type" : "literal",
        "value" : "Méline Rollin"
      },
      "itemDescription" : {
        "xml:lang" : "en",
        "type" : "literal",
        "value" : "French long-distance runner"
      },
      "articlename" : {
        "xml:lang" : "fr",
        "type" : "literal",
        "value" : "Méline Rollin"
      }
    } ]
  }
}